{
  "country_code": "AO",
  "country_name": "Angola",
  "total_airports": 122,
  "last_updated": "2025-04-26T00:08:25.646498",
  "types_distribution": {
    "small_airport": 87,
    "closed": 11,
    "heliport": 2,
    "medium_airport": 21,
    "large_airport": 1
  },
  "airports": [
    {
      "ident": "AO-0001",
      "type": "small_airport",
      "name": "Catoca Airport",
      "elevation_ft": 3498.0,
      "continent": "AF",
      "iso_country": "AO",
      "iso_region": "AO-LSU",
      "municipality": "Saurimo",
      "gps_code": "FNCO",
      "iata_code": "CTV",
      "coordinates": "-9.431359, 20.311557"
    },
    {
      "ident": "AO-0002",
      "type": "small_airport",
      "name": "Nancova Airport",
      "continent": "AF",
      "iso_country": "AO",
      "iso_region": "AO-CCU",
      "municipality": "Nancova",
      "coordinates": "-16.39637, 18.978764"
    },
    {
      "ident": "AO-0003",
      "type": "small_airport",
      "name": "Rito Airport",
      "continent": "AF",
      "iso_country": "AO",
      "iso_region": "AO-CCU",
      "municipality": "Rito",
      "coordinates": "-16.689392, 19.083767"
    },
    {
      "ident": "AO-0004",
      "type": "small_airport",
      "name": "Coemba Airport",
      "continent": "AF",
      "iso_country": "AO",
      "iso_region": "AO-BIE",
      "municipality": "Coemba",
      "coordinates": "-12.143704, 18.085363"
    },
    {
      "ident": "AO-0005",
      "type": "small_airport",
      "name": "Andulo Airport",
      "continent": "AF",
      "iso_country": "AO",
      "iso_region": "AO-BIE",
      "municipality": "Andulo",
      "iata_code": "ANL",
      "coordinates": "-11.4723, 16.710899"
    },
    {
      "ident": "AO-0006",
      "type": "small_airport",
      "name": "Caluquembe Airport",
      "continent": "AF",
      "iso_country": "AO",
      "iso_region": "AO-HUI",
      "municipality": "Calequembe",
      "coordinates": "-13.775546, 14.694916"
    },
    {
      "ident": "AO-0007",
      "type": "small_airport",
      "name": "Cuvelai Airport",
      "continent": "AF",
      "iso_country": "AO",
      "iso_region": "AO-CNN",
      "municipality": "Cuvelai",
      "coordinates": "-15.668575, 15.805654"
    },
    {
      "ident": "AO-0008",
      "type": "small_airport",
      "name": "Cuangar Airport",
      "continent": "AF",
      "iso_country": "AO",
      "iso_region": "AO-CCU",
      "municipality": "Cuangar",
      "coordinates": "-17.597122, 18.63437"
    },
    {
      "ident": "AO-0009",
      "type": "closed",
      "name": "Cuangar Old Airport",
      "continent": "AF",
      "iso_country": "AO",
      "iso_region": "AO-CCU",
      "municipality": "Cuangar",
      "coordinates": "-17.599985, 18.623552"
    },
    {
      "ident": "AO-0010",
      "type": "closed",
      "name": "Savate Airport",
      "continent": "AF",
      "iso_country": "AO",
      "iso_region": "AO-CCU",
      "municipality": "Savate",
      "coordinates": "-16.88068, 18.001893"
    },
    {
      "ident": "AO-0011",
      "type": "small_airport",
      "name": "Mucusso Airport",
      "continent": "AF",
      "iso_country": "AO",
      "iso_region": "AO-CCU",
      "municipality": "Mucusso",
      "coordinates": "-18.020826, 21.437053"
    },
    {
      "ident": "AO-0012",
      "type": "small_airport",
      "name": "Jamba Airport",
      "continent": "AF",
      "iso_country": "AO",
      "iso_region": "AO-CCU",
      "municipality": "Jamba",
      "coordinates": "-17.454765, 22.607245"
    },
    {
      "ident": "AO-0013",
      "type": "closed",
      "name": "Luiana Airport",
      "continent": "AF",
      "iso_country": "AO",
      "iso_region": "AO-CCU",
      "municipality": "Luiana",
      "coordinates": "-17.380791, 23.002339"
    },
    {
      "ident": "AO-0014",
      "type": "closed",
      "name": "Coutada Airport",
      "continent": "AF",
      "iso_country": "AO",
      "iso_region": "AO-CCU",
      "municipality": "Coutada",
      "coordinates": "-17.017654, 21.301774"
    },
    {
      "ident": "AO-0015",
      "type": "closed",
      "name": "Rivungo Airport",
      "continent": "AF",
      "iso_country": "AO",
      "iso_region": "AO-CCU",
      "municipality": "Rivungo",
      "coordinates": "-15.793551, 21.380704"
    },
    {
      "ident": "AO-0016",
      "type": "small_airport",
      "name": "Mavinga Airport",
      "continent": "AF",
      "iso_country": "AO",
      "iso_region": "AO-CCU",
      "municipality": "Mavinga",
      "coordinates": "-15.789222, 20.368971"
    },
    {
      "ident": "AO-0017",
      "type": "small_airport",
      "name": "Ninda Airport",
      "continent": "AF",
      "iso_country": "AO",
      "iso_region": "AO-MOX",
      "municipality": "Ninda",
      "coordinates": "-14.80893, 21.376961"
    },
    {
      "ident": "AO-0018",
      "type": "closed",
      "name": "Luena Airport",
      "continent": "AF",
      "iso_country": "AO",
      "iso_region": "AO-MOX",
      "municipality": "Luena",
      "coordinates": "-12.740271, 20.736829"
    },
    {
      "ident": "AO-0019",
      "type": "small_airport",
      "name": "Lucusse Airport",
      "continent": "AF",
      "iso_country": "AO",
      "iso_region": "AO-MOX",
      "municipality": "Lucusse",
      "coordinates": "-12.521974, 20.805726"
    },
    {
      "ident": "AO-0020",
      "type": "small_airport",
      "name": "Cassamba Airport",
      "continent": "AF",
      "iso_country": "AO",
      "iso_region": "AO-MOX",
      "municipality": "Cassamba",
      "coordinates": "-13.139351, 20.300824"
    },
    {
      "ident": "AO-0021",
      "type": "small_airport",
      "name": "Calunda Airport",
      "continent": "AF",
      "iso_country": "AO",
      "iso_region": "AO-MOX",
      "municipality": "Calunda",
      "coordinates": "-12.126335, 23.478615"
    },
    {
      "ident": "AO-0022",
      "type": "small_airport",
      "name": "Lóvua Airport",
      "continent": "AF",
      "iso_country": "AO",
      "iso_region": "AO-MOX",
      "municipality": "Lóvua",
      "coordinates": "-11.556065, 23.553667"
    },
    {
      "ident": "AO-0023",
      "type": "small_airport",
      "name": "Luacano Airport",
      "continent": "AF",
      "iso_country": "AO",
      "iso_region": "AO-MOX",
      "municipality": "Luacano",
      "coordinates": "-11.209962, 21.648705"
    },
    {
      "ident": "AO-0024",
      "type": "small_airport",
      "name": "Lumeje Airport",
      "continent": "AF",
      "iso_country": "AO",
      "iso_region": "AO-MOX",
      "municipality": "Lumeje",
      "coordinates": "-11.564598, 20.785903"
    },
    {
      "ident": "AO-0025",
      "type": "small_airport",
      "name": "Chipato Airport",
      "continent": "AF",
      "iso_country": "AO",
      "iso_region": "AO-MOX",
      "municipality": "Luao",
      "coordinates": "-10.701382, 22.160291"
    },
    {
      "ident": "AO-0026",
      "type": "closed",
      "name": "Nova Chaves Airport",
      "continent": "AF",
      "iso_country": "AO",
      "iso_region": "AO-LSU",
      "municipality": "Nova Chaves",
      "coordinates": "-10.598408, 21.315093"
    },
    {
      "ident": "AO-0027",
      "type": "small_airport",
      "name": "Camacupa Airport",
      "continent": "AF",
      "iso_country": "AO",
      "iso_region": "AO-BIE",
      "municipality": "Camacupa",
      "coordinates": "-12.021878, 17.453693"
    },
    {
      "ident": "AO-0028",
      "type": "small_airport",
      "name": "Luando Airport",
      "continent": "AF",
      "iso_country": "AO",
      "iso_region": "AO-BIE",
      "municipality": "Luando",
      "coordinates": "-11.62444, 18.46969"
    },
    {
      "ident": "AO-0029",
      "type": "small_airport",
      "name": "Quirima Airport",
      "continent": "AF",
      "iso_country": "AO",
      "iso_region": "AO-MAL",
      "municipality": "Quirima",
      "coordinates": "-10.902645, 18.060368"
    },
    {
      "ident": "AO-0030",
      "type": "small_airport",
      "name": "Dala Airport",
      "continent": "AF",
      "iso_country": "AO",
      "iso_region": "AO-LSU",
      "municipality": "Dala",
      "coordinates": "-11.040653, 20.208268"
    },
    {
      "ident": "AO-0031",
      "type": "closed",
      "name": "Cazaje Airport",
      "continent": "AF",
      "iso_country": "AO",
      "iso_region": "AO-LSU",
      "municipality": "Cazaje",
      "coordinates": "-11.063437, 20.695914"
    },
    {
      "ident": "AO-0032",
      "type": "small_airport",
      "name": "Longa Airport",
      "continent": "AF",
      "iso_country": "AO",
      "iso_region": "AO-CCU",
      "municipality": "Longa",
      "coordinates": "-14.610741, 18.487945"
    },
    {
      "ident": "AO-0033",
      "type": "small_airport",
      "name": "Cuchi Airport",
      "continent": "AF",
      "iso_country": "AO",
      "iso_region": "AO-CCU",
      "municipality": "Cuchi",
      "coordinates": "-14.64987, 16.885391"
    },
    {
      "ident": "AO-0034",
      "type": "small_airport",
      "name": "Mutumbo Airport",
      "elevation_ft": 4773.0,
      "continent": "AF",
      "iso_country": "AO",
      "iso_region": "AO-BIE",
      "municipality": "Mutumbo",
      "coordinates": "-13.179982, 17.394938"
    },
    {
      "ident": "AO-0035",
      "type": "small_airport",
      "name": "Miguel Airport",
      "continent": "AF",
      "iso_country": "AO",
      "iso_region": "AO-CCU",
      "municipality": "Miguel",
      "coordinates": "-15.704318, 17.452439"
    },
    {
      "ident": "AO-0036",
      "type": "closed",
      "name": "Namacunde Airport",
      "continent": "AF",
      "iso_country": "AO",
      "iso_region": "AO-CNN",
      "municipality": "Namacunde",
      "coordinates": "-17.302638, 15.850786"
    },
    {
      "ident": "AO-0037",
      "type": "small_airport",
      "name": "Calai Airport",
      "continent": "AF",
      "iso_country": "AO",
      "iso_region": "AO-CCU",
      "municipality": "Calai",
      "coordinates": "-17.878868, 19.782762"
    },
    {
      "ident": "AO-0038",
      "type": "small_airport",
      "name": "Chitado Airport",
      "continent": "AF",
      "iso_country": "AO",
      "iso_region": "AO-CNN",
      "municipality": "Chitado",
      "coordinates": "-17.320733, 13.923845"
    },
    {
      "ident": "AO-0039",
      "type": "small_airport",
      "name": "Alto Dondo Airport",
      "continent": "AF",
      "iso_country": "AO",
      "iso_region": "AO-CNO",
      "municipality": "Dondo",
      "coordinates": "-9.675516, 14.464999"
    },
    {
      "ident": "AO-0040",
      "type": "small_airport",
      "name": "Mussende Airport",
      "continent": "AF",
      "iso_country": "AO",
      "iso_region": "AO-CUS",
      "municipality": "Mussende",
      "coordinates": "-10.520306, 15.99677"
    },
    {
      "ident": "AO-0041",
      "type": "small_airport",
      "name": "Capenda Camulemba Airport",
      "continent": "AF",
      "iso_country": "AO",
      "iso_region": "AO-LNO",
      "municipality": "Capenda Camulemba",
      "coordinates": "-9.415833, 18.434794"
    },
    {
      "ident": "AO-0042",
      "type": "small_airport",
      "name": "Xassengue Airport",
      "continent": "AF",
      "iso_country": "AO",
      "iso_region": "AO-LSU",
      "municipality": "Xassengue",
      "coordinates": "-10.461305, 18.535527"
    },
    {
      "ident": "AO-0043",
      "type": "small_airport",
      "name": "Balombo Airport",
      "continent": "AF",
      "iso_country": "AO",
      "iso_region": "AO-BGU",
      "municipality": "Balombo",
      "coordinates": "-12.357134, 14.77923"
    },
    {
      "ident": "AO-0044",
      "type": "small_airport",
      "name": "Cuima Airport",
      "continent": "AF",
      "iso_country": "AO",
      "iso_region": "AO-HUA",
      "municipality": "Cuima",
      "coordinates": "-13.458467, 15.833762"
    },
    {
      "ident": "AO-0045",
      "type": "small_airport",
      "name": "Cubati Airport",
      "elevation_ft": 4121.0,
      "continent": "AF",
      "iso_country": "AO",
      "iso_region": "AO-CNN",
      "municipality": "Cubati",
      "coordinates": "-15.333917, 16.851872"
    },
    {
      "ident": "AO-0046",
      "type": "small_airport",
      "name": "Capelongo Airport",
      "continent": "AF",
      "iso_country": "AO",
      "iso_region": "AO-HUI",
      "municipality": "Capelongo",
      "coordinates": "-14.457297, 16.296202"
    },
    {
      "ident": "AO-0047",
      "type": "small_airport",
      "name": "Chitembo Airport",
      "elevation_ft": 5393.0,
      "continent": "AF",
      "iso_country": "AO",
      "iso_region": "AO-BIE",
      "municipality": "Chitembo",
      "coordinates": "-13.509385, 16.74928"
    },
    {
      "ident": "AO-0048",
      "type": "small_airport",
      "name": "Cuito Cuanavale South Airport",
      "continent": "AF",
      "iso_country": "AO",
      "iso_region": "AO-CCU",
      "municipality": "Baixo Longa",
      "coordinates": "-15.711983, 18.651003"
    },
    {
      "ident": "AO-0049",
      "type": "small_airport",
      "name": "Mussuma Airport",
      "elevation_ft": 3477.0,
      "continent": "AF",
      "iso_country": "AO",
      "iso_region": "AO-MOX",
      "municipality": "Mussuma",
      "coordinates": "-14.204202, 21.909971"
    },
    {
      "ident": "AO-0050",
      "type": "small_airport",
      "name": "Mumbué Airport",
      "elevation_ft": 4995.0,
      "continent": "AF",
      "iso_country": "AO",
      "iso_region": "AO-BIE",
      "municipality": "Mumbué",
      "coordinates": "-13.900039, 17.300036"
    },
    {
      "ident": "AO-0051",
      "type": "small_airport",
      "name": "Cubango River Airport",
      "elevation_ft": 5073.0,
      "continent": "AF",
      "iso_country": "AO",
      "iso_region": "AO-HUA",
      "municipality": "Hungulo",
      "coordinates": "-13.333366, 16.414531"
    },
    {
      "ident": "AO-0052",
      "type": "small_airport",
      "name": "Chinhama Airport",
      "elevation_ft": 5565.0,
      "continent": "AF",
      "iso_country": "AO",
      "iso_region": "AO-HUA",
      "municipality": "Chinhama",
      "coordinates": "-13.105437, 16.42432"
    },
    {
      "ident": "AO-0053",
      "type": "small_airport",
      "name": "Baía dos Tigres Airstrip",
      "continent": "AF",
      "iso_country": "AO",
      "iso_region": "AO-NAM",
      "municipality": "Vila Baía dos Tigres",
      "coordinates": "-16.6023, 11.7222"
    },
    {
      "ident": "AO-0054",
      "type": "closed",
      "name": "Tômbua Airport",
      "elevation_ft": 144.0,
      "continent": "AF",
      "iso_country": "AO",
      "iso_region": "AO-NAM",
      "municipality": "Tômbua",
      "coordinates": "-15.800486, 11.885896"
    },
    {
      "ident": "AO-0055",
      "type": "small_airport",
      "name": "Bentiaba Airfield",
      "continent": "AF",
      "iso_country": "AO",
      "iso_region": "AO-NAM",
      "municipality": "Bentiaba",
      "coordinates": "-14.25396, 12.39103"
    },
    {
      "ident": "AO-0056",
      "type": "small_airport",
      "name": "Lunuango Airstrip",
      "continent": "AF",
      "iso_country": "AO",
      "iso_region": "AO-ZAI",
      "municipality": "Lunuango",
      "coordinates": "-6.4594, 12.5697"
    },
    {
      "ident": "AO-0057",
      "type": "small_airport",
      "name": "Kwanda Airport",
      "continent": "AF",
      "iso_country": "AO",
      "iso_region": "AO-ZAI",
      "municipality": "Soyo",
      "coordinates": "-6.1244, 12.328"
    },
    {
      "ident": "AO-0058",
      "type": "heliport",
      "name": "Sinfo Heliport",
      "continent": "AF",
      "iso_country": "AO",
      "iso_region": "AO-LUA",
      "municipality": "Luanda",
      "coordinates": "-8.91811, 13.25935"
    },
    {
      "ident": "AO-0059",
      "type": "small_airport",
      "name": "Emilio de Carvalho Airport",
      "elevation_ft": 36.0,
      "continent": "AF",
      "iso_country": "AO",
      "iso_region": "AO-ZAI",
      "municipality": "Emilio de Carvalho",
      "coordinates": "-5.93365, 12.96583"
    },
    {
      "ident": "AO-0060",
      "type": "small_airport",
      "name": "Nhamuana Airport",
      "elevation_ft": 3530.0,
      "continent": "AF",
      "iso_country": "AO",
      "iso_region": "AO-MOX",
      "municipality": "Nhamuana",
      "coordinates": "-12.99457, 22.7275"
    },
    {
      "ident": "AO-0061",
      "type": "closed",
      "name": "Aldeia Airport",
      "elevation_ft": 3812.0,
      "continent": "AF",
      "iso_country": "AO",
      "iso_region": "AO-CCU",
      "municipality": "Aldeia",
      "coordinates": "-16.21254, 17.67218"
    },
    {
      "ident": "AO-0062",
      "type": "small_airport",
      "name": "Bicunga Airport",
      "elevation_ft": 5270.0,
      "continent": "AF",
      "iso_country": "AO",
      "iso_region": "AO-HUI",
      "municipality": "Bicunga",
      "coordinates": "-13.78708, 16.44915"
    },
    {
      "ident": "AO-0063",
      "type": "small_airport",
      "name": "Tchindjenje Airport",
      "elevation_ft": 4501.0,
      "continent": "AF",
      "iso_country": "AO",
      "iso_region": "AO-HUA",
      "municipality": "Tchindjenje",
      "coordinates": "-12.82279, 14.93308"
    },
    {
      "ident": "AO-0064",
      "type": "small_airport",
      "name": "Ganda Airport",
      "elevation_ft": 4170.0,
      "continent": "AF",
      "iso_country": "AO",
      "iso_region": "AO-BGU",
      "municipality": "Ganda",
      "coordinates": "-12.99473, 14.64698"
    },
    {
      "ident": "AO-0065",
      "type": "small_airport",
      "name": "Caimbambo Airport",
      "elevation_ft": 2667.0,
      "continent": "AF",
      "iso_country": "AO",
      "iso_region": "AO-BGU",
      "municipality": "Caimbambo",
      "coordinates": "-13.04186, 13.99673"
    },
    {
      "ident": "AO-0066",
      "type": "heliport",
      "name": "Malongo Terminal Heliport",
      "continent": "AF",
      "iso_country": "AO",
      "iso_region": "AO-CAB",
      "municipality": "Malongo",
      "coordinates": "-5.395639, 12.212859"
    },
    {
      "ident": "AO-0067",
      "type": "small_airport",
      "name": "Lumbala Airstrip",
      "elevation_ft": 3510.0,
      "continent": "AF",
      "iso_country": "AO",
      "iso_region": "AO-MOX",
      "municipality": "Lumbala",
      "coordinates": "-12.639877, 22.586821"
    },
    {
      "ident": "AO-0068",
      "type": "small_airport",
      "name": "Espinheira Airfield",
      "elevation_ft": 1493.0,
      "continent": "AF",
      "iso_country": "AO",
      "iso_region": "AO-NAM",
      "municipality": "Espinheira",
      "coordinates": "-16.78214, 12.35133"
    },
    {
      "ident": "AO-0069",
      "type": "small_airport",
      "name": "Praia do Capim Airfield",
      "elevation_ft": 33.0,
      "continent": "AF",
      "iso_country": "AO",
      "iso_region": "AO-NAM",
      "municipality": "Praia do Capim",
      "coordinates": "-15.73555, 11.92488"
    },
    {
      "ident": "AO-0070",
      "type": "small_airport",
      "name": "Dombe Grande Airfield",
      "elevation_ft": 294.0,
      "continent": "AF",
      "iso_country": "AO",
      "iso_region": "AO-BGU",
      "municipality": "Dombe Grande",
      "coordinates": "-13.00966, 13.10344"
    },
    {
      "ident": "AO-0071",
      "type": "small_airport",
      "name": "Canhoca Airstrip",
      "elevation_ft": 469.0,
      "continent": "AF",
      "iso_country": "AO",
      "iso_region": "AO-BGU",
      "municipality": "Canhoca",
      "coordinates": "-13.41936, 12.56508"
    },
    {
      "ident": "AO-CNZ",
      "type": "small_airport",
      "name": "Cangamba Airport",
      "elevation_ft": 3894.0,
      "continent": "AF",
      "iso_country": "AO",
      "iso_region": "AO-MOX",
      "municipality": "Cangamba",
      "iata_code": "CNZ",
      "coordinates": "-13.7106, 19.861099"
    },
    {
      "ident": "AO-DRC",
      "type": "small_airport",
      "name": "Dirico Airport",
      "elevation_ft": 3504.0,
      "continent": "AF",
      "iso_country": "AO",
      "iso_region": "AO-CCU",
      "municipality": "Dirico",
      "iata_code": "DRC",
      "coordinates": "-17.981924, 20.768061"
    },
    {
      "ident": "AO-NDF",
      "type": "small_airport",
      "name": "N'dalatando Airport",
      "elevation_ft": 2684.0,
      "continent": "AF",
      "iso_country": "AO",
      "iso_region": "AO-CNO",
      "municipality": "N'dalatando",
      "iata_code": "NDF",
      "coordinates": "-9.280378, 14.982432"
    },
    {
      "ident": "FN17",
      "type": "small_airport",
      "name": "Cahama Airport",
      "elevation_ft": 3970.0,
      "continent": "AF",
      "iso_country": "AO",
      "iso_region": "AO-CNN",
      "municipality": "Cahama",
      "gps_code": "FN17",
      "coordinates": "-16.238399505615234, 14.326000213623047"
    },
    {
      "ident": "FN18",
      "type": "small_airport",
      "name": "Matala Airport",
      "elevation_ft": 4120.0,
      "continent": "AF",
      "iso_country": "AO",
      "iso_region": "AO-HUI",
      "municipality": "Matala",
      "gps_code": "FN18",
      "local_code": "FN18",
      "coordinates": "-14.727499961853027, 15.013999938964844"
    },
    {
      "ident": "FN19",
      "type": "small_airport",
      "name": "Cabo Ledo Air Base",
      "elevation_ft": 360.0,
      "continent": "AF",
      "iso_country": "AO",
      "iso_region": "AO-LUA",
      "municipality": "Cabo Ledo",
      "gps_code": "FN19",
      "local_code": "FN19",
      "coordinates": "-9.65305, 13.2606"
    },
    {
      "ident": "FNAM",
      "type": "small_airport",
      "name": "Ambriz Airport",
      "elevation_ft": 144.0,
      "continent": "AF",
      "iso_country": "AO",
      "iso_region": "AO-BGO",
      "municipality": "Ambriz",
      "gps_code": "FNAM",
      "iata_code": "AZZ",
      "coordinates": "-7.86222, 13.1161"
    },
    {
      "ident": "FNBC",
      "type": "medium_airport",
      "name": "Mbanza Congo Airport",
      "elevation_ft": 1860.0,
      "continent": "AF",
      "iso_country": "AO",
      "iso_region": "AO-ZAI",
      "municipality": "Mbanza Congo",
      "gps_code": "FNBC",
      "iata_code": "SSY",
      "coordinates": "-6.269899845123291, 14.246999740600586"
    },
    {
      "ident": "FNBG",
      "type": "medium_airport",
      "name": "Benguela 17th of September Airport",
      "elevation_ft": 118.0,
      "continent": "AF",
      "iso_country": "AO",
      "iso_region": "AO-BGU",
      "municipality": "Benguela",
      "gps_code": "FNBG",
      "iata_code": "BUG",
      "coordinates": "-12.609, 13.4037"
    },
    {
      "ident": "FNBJ",
      "type": "medium_airport",
      "name": "Dr. Antonio Agostinho Neto International Airport",
      "elevation_ft": 550.0,
      "continent": "AF",
      "iso_country": "AO",
      "iso_region": "AO-LUA",
      "municipality": "Luanda (Ícolo e Bengo)",
      "gps_code": "FNBJ",
      "iata_code": "NBJ",
      "coordinates": "-9.050734, 13.499078"
    },
    {
      "ident": "FNBL",
      "type": "small_airport",
      "name": "Lumbala Airport",
      "elevation_ft": 3700.0,
      "continent": "AF",
      "iso_country": "AO",
      "iso_region": "AO-MOX",
      "municipality": "Lumbala N'guimbo",
      "gps_code": "FNBL",
      "iata_code": "GGC",
      "coordinates": "-14.105106, 21.45083"
    },
    {
      "ident": "FNCA",
      "type": "medium_airport",
      "name": "Cabinda Airport",
      "elevation_ft": 66.0,
      "continent": "AF",
      "iso_country": "AO",
      "iso_region": "AO-CAB",
      "municipality": "Cabinda",
      "gps_code": "FNCA",
      "iata_code": "CAB",
      "coordinates": "-5.59699010848999, 12.188400268554688"
    },
    {
      "ident": "FNCB",
      "type": "small_airport",
      "name": "Camembe Airport",
      "elevation_ft": 2264.0,
      "continent": "AF",
      "iso_country": "AO",
      "iso_region": "AO-BGO",
      "municipality": "Camembe",
      "gps_code": "FNCB",
      "coordinates": "-8.119819, 14.498963"
    },
    {
      "ident": "FNCC",
      "type": "small_airport",
      "name": "Cacolo Airport",
      "elevation_ft": 4400.0,
      "continent": "AF",
      "iso_country": "AO",
      "iso_region": "AO-LSU",
      "municipality": "Cacolo",
      "gps_code": "FNCC",
      "coordinates": "-10.110278, 19.287304"
    },
    {
      "ident": "FNCF",
      "type": "small_airport",
      "name": "Cafunfo Airport",
      "continent": "AF",
      "iso_country": "AO",
      "iso_region": "AO-LNO",
      "municipality": "Cafunfo",
      "gps_code": "FNCF",
      "iata_code": "CFF",
      "coordinates": "-8.78361, 17.9897"
    },
    {
      "ident": "FNCH",
      "type": "small_airport",
      "name": "Chitato Airport",
      "elevation_ft": 2500.0,
      "continent": "AF",
      "iso_country": "AO",
      "iso_region": "AO-LNO",
      "municipality": "Chitato",
      "gps_code": "FNCH",
      "iata_code": "PGI",
      "coordinates": "-7.35889, 20.804701"
    },
    {
      "ident": "FNCM",
      "type": "small_airport",
      "name": "Camabatela Airport",
      "elevation_ft": 410.0,
      "continent": "AF",
      "iso_country": "AO",
      "iso_region": "AO-CNO",
      "municipality": "Camabatela",
      "gps_code": "FNCM",
      "coordinates": "-8.177847, 15.383177"
    },
    {
      "ident": "FNCP",
      "type": "small_airport",
      "name": "Capanda Airport",
      "elevation_ft": 3366.0,
      "continent": "AF",
      "iso_country": "AO",
      "iso_region": "AO-MAL",
      "municipality": "Capanda",
      "gps_code": "FNCP",
      "iata_code": "KNP",
      "coordinates": "-9.76937007904, 15.4553194046"
    },
    {
      "ident": "FNCT",
      "type": "medium_airport",
      "name": "Catumbela Airport",
      "elevation_ft": 23.0,
      "continent": "AF",
      "iso_country": "AO",
      "iso_region": "AO-BGU",
      "municipality": "Catumbela",
      "gps_code": "FNCT",
      "iata_code": "CBT",
      "coordinates": "-12.4792, 13.4869"
    },
    {
      "ident": "FNCV",
      "type": "small_airport",
      "name": "Cuito Cuanavale Airport",
      "continent": "AF",
      "iso_country": "AO",
      "iso_region": "AO-CCU",
      "municipality": "Cuito Cuanavale",
      "gps_code": "FNCV",
      "iata_code": "CTI",
      "coordinates": "-15.1603, 19.156099"
    },
    {
      "ident": "FNCX",
      "type": "small_airport",
      "name": "Camaxilo Airport",
      "elevation_ft": 3957.0,
      "continent": "AF",
      "iso_country": "AO",
      "iso_region": "AO-LNO",
      "municipality": "Camaxilo",
      "gps_code": "FNCX",
      "iata_code": "CXM",
      "coordinates": "-8.37361, 18.923599"
    },
    {
      "ident": "FNCZ",
      "type": "small_airport",
      "name": "Cazombo Airport",
      "elevation_ft": 3700.0,
      "continent": "AF",
      "iso_country": "AO",
      "iso_region": "AO-MOX",
      "municipality": "Cazombo",
      "gps_code": "FNCZ",
      "iata_code": "CAV",
      "coordinates": "-11.8931, 22.916239"
    },
    {
      "ident": "FNDB",
      "type": "small_airport",
      "name": "Damba Airport",
      "elevation_ft": 3648.0,
      "continent": "AF",
      "iso_country": "AO",
      "iso_region": "AO-UIG",
      "municipality": "Damba",
      "gps_code": "FNDB",
      "coordinates": "-6.9, 15.133"
    },
    {
      "ident": "FNDU",
      "type": "medium_airport",
      "name": "Dundo Airport",
      "elevation_ft": 2451.0,
      "continent": "AF",
      "iso_country": "AO",
      "iso_region": "AO-LNO",
      "municipality": "Chitato",
      "gps_code": "FNDU",
      "iata_code": "DUE",
      "coordinates": "-7.400889873504639, 20.818500518798828"
    },
    {
      "ident": "FNGI",
      "type": "medium_airport",
      "name": "Ngjiva Pereira Airport",
      "elevation_ft": 3566.0,
      "continent": "AF",
      "iso_country": "AO",
      "iso_region": "AO-CNN",
      "municipality": "Ngiva",
      "gps_code": "FNGI",
      "iata_code": "VPE",
      "coordinates": "-17.0435009003, 15.683799743700002"
    },
    {
      "ident": "FNHU",
      "type": "medium_airport",
      "name": "Nova Lisboa Airport",
      "elevation_ft": 5587.0,
      "continent": "AF",
      "iso_country": "AO",
      "iso_region": "AO-HUA",
      "municipality": "Huambo",
      "gps_code": "FNHU",
      "iata_code": "NOV",
      "coordinates": "-12.808899879455566, 15.760499954223633"
    },
    {
      "ident": "FNKU",
      "type": "medium_airport",
      "name": "Kuito Airport",
      "elevation_ft": 5618.0,
      "continent": "AF",
      "iso_country": "AO",
      "iso_region": "AO-BIE",
      "municipality": "Kuito",
      "gps_code": "FNKU",
      "iata_code": "SVP",
      "coordinates": "-12.404600143433, 16.947399139404"
    },
    {
      "ident": "FNLB",
      "type": "small_airport",
      "name": "Lobito Airport",
      "elevation_ft": 10.0,
      "continent": "AF",
      "iso_country": "AO",
      "iso_region": "AO-BGU",
      "municipality": "Lobito",
      "gps_code": "FNLB",
      "iata_code": "LLT",
      "coordinates": "-12.3712, 13.5366"
    },
    {
      "ident": "FNLK",
      "type": "small_airport",
      "name": "Lucapa Airport",
      "elevation_ft": 3029.0,
      "continent": "AF",
      "iso_country": "AO",
      "iso_region": "AO-LNO",
      "municipality": "Lucapa",
      "gps_code": "FNLK",
      "iata_code": "LBZ",
      "coordinates": "-8.445727348330001, 20.7320861816"
    },
    {
      "ident": "FNLU",
      "type": "large_airport",
      "name": "Quatro de Fevereiro International Airport",
      "elevation_ft": 243.0,
      "continent": "AF",
      "iso_country": "AO",
      "iso_region": "AO-LUA",
      "municipality": "Luanda",
      "gps_code": "FNLU",
      "iata_code": "LAD",
      "coordinates": "-8.85837, 13.2312"
    },
    {
      "ident": "FNLZ",
      "type": "small_airport",
      "name": "Luzamba Airport",
      "elevation_ft": 2904.0,
      "continent": "AF",
      "iso_country": "AO",
      "iso_region": "AO-LNO",
      "municipality": "Luzamba",
      "gps_code": "FNLZ",
      "iata_code": "LZM",
      "coordinates": "-9.11596012115, 18.049299240099998"
    },
    {
      "ident": "FNMA",
      "type": "medium_airport",
      "name": "Malanje Airport",
      "elevation_ft": 3868.0,
      "continent": "AF",
      "iso_country": "AO",
      "iso_region": "AO-MAL",
      "municipality": "Malanje",
      "gps_code": "FNMA",
      "iata_code": "MEG",
      "coordinates": "-9.525090217590332, 16.312400817871094"
    },
    {
      "ident": "FNME",
      "type": "medium_airport",
      "name": "Menongue Airport",
      "elevation_ft": 4469.0,
      "continent": "AF",
      "iso_country": "AO",
      "iso_region": "AO-CCU",
      "municipality": "Menongue",
      "gps_code": "FNME",
      "iata_code": "SPP",
      "coordinates": "-14.657600402832031, 17.71980094909668"
    },
    {
      "ident": "FNMO",
      "type": "medium_airport",
      "name": "Welwitschia Mirabilis International Airport",
      "elevation_ft": 210.0,
      "continent": "AF",
      "iso_country": "AO",
      "iso_region": "AO-NAM",
      "municipality": "Moçâmedes",
      "gps_code": "FNMO",
      "iata_code": "MSZ",
      "coordinates": "-15.2612, 12.1468"
    },
    {
      "ident": "FNMQ",
      "type": "small_airport",
      "name": "Maquela do Zombo Airport",
      "elevation_ft": 3051.0,
      "continent": "AF",
      "iso_country": "AO",
      "iso_region": "AO-UIG",
      "municipality": "Maquela do Zombo",
      "gps_code": "FNMQ",
      "coordinates": "-6.03028, 15.1369"
    },
    {
      "ident": "FNNG",
      "type": "medium_airport",
      "name": "Negage Airport",
      "elevation_ft": 4105.0,
      "continent": "AF",
      "iso_country": "AO",
      "iso_region": "AO-UIG",
      "municipality": "Negage",
      "gps_code": "FNNG",
      "iata_code": "GXG",
      "coordinates": "-7.754509925842285, 15.287699699401855"
    },
    {
      "ident": "FNPA",
      "type": "medium_airport",
      "name": "Porto Amboim Airport",
      "elevation_ft": 16.0,
      "continent": "AF",
      "iso_country": "AO",
      "iso_region": "AO-CUS",
      "municipality": "Port Amboim",
      "gps_code": "FNPA",
      "iata_code": "PBN",
      "coordinates": "-10.722, 13.7655"
    },
    {
      "ident": "FNPB",
      "type": "small_airport",
      "name": "Sanza Pombo Airport",
      "elevation_ft": 3251.0,
      "continent": "AF",
      "iso_country": "AO",
      "iso_region": "AO-UIG",
      "municipality": "Sanza Pombo",
      "gps_code": "FNPB",
      "coordinates": "-7.288999, 15.930191"
    },
    {
      "ident": "FNSA",
      "type": "medium_airport",
      "name": "Saurimo Airport",
      "elevation_ft": 3584.0,
      "continent": "AF",
      "iso_country": "AO",
      "iso_region": "AO-LSU",
      "municipality": "Saurimo",
      "gps_code": "FNSA",
      "iata_code": "VHC",
      "coordinates": "-9.68907, 20.4319"
    },
    {
      "ident": "FNSO",
      "type": "medium_airport",
      "name": "Soyo Airport",
      "elevation_ft": 15.0,
      "continent": "AF",
      "iso_country": "AO",
      "iso_region": "AO-ZAI",
      "municipality": "Soyo",
      "gps_code": "FNSO",
      "iata_code": "SZA",
      "coordinates": "-6.141089916229248, 12.371800422668457"
    },
    {
      "ident": "FNSU",
      "type": "medium_airport",
      "name": "Sumbe Airport",
      "elevation_ft": 36.0,
      "continent": "AF",
      "iso_country": "AO",
      "iso_region": "AO-CUS",
      "municipality": "Sumbe",
      "gps_code": "FNSU",
      "iata_code": "NDD",
      "coordinates": "-11.1679, 13.8475"
    },
    {
      "ident": "FNTO",
      "type": "small_airport",
      "name": "Toto Airport",
      "elevation_ft": 1775.0,
      "continent": "AF",
      "iso_country": "AO",
      "iso_region": "AO-UIG",
      "municipality": "Toto",
      "gps_code": "FNTO",
      "coordinates": "-7.14639, 14.2486"
    },
    {
      "ident": "FNUA",
      "type": "small_airport",
      "name": "Luau Airport",
      "elevation_ft": 3609.0,
      "continent": "AF",
      "iso_country": "AO",
      "iso_region": "AO-MOX",
      "municipality": "Luau",
      "gps_code": "FNUA",
      "iata_code": "UAL",
      "coordinates": "-10.7158, 22.2311"
    },
    {
      "ident": "FNUB",
      "type": "medium_airport",
      "name": "Lubango Airport",
      "elevation_ft": 5778.0,
      "continent": "AF",
      "iso_country": "AO",
      "iso_region": "AO-HUI",
      "municipality": "Lubango",
      "gps_code": "FNUB",
      "iata_code": "SDD",
      "coordinates": "-14.924699783325195, 13.574999809265137"
    },
    {
      "ident": "FNUE",
      "type": "medium_airport",
      "name": "Luena Airport",
      "elevation_ft": 4360.0,
      "continent": "AF",
      "iso_country": "AO",
      "iso_region": "AO-MOX",
      "municipality": "Luena",
      "gps_code": "FNUE",
      "iata_code": "LUO",
      "coordinates": "-11.7681, 19.897699"
    },
    {
      "ident": "FNUG",
      "type": "medium_airport",
      "name": "Uige Airport",
      "elevation_ft": 2720.0,
      "continent": "AF",
      "iso_country": "AO",
      "iso_region": "AO-UIG",
      "municipality": "Uige",
      "gps_code": "FNUG",
      "iata_code": "UGO",
      "coordinates": "-7.60307, 15.0278"
    },
    {
      "ident": "FNWK",
      "type": "small_airport",
      "name": "Waco Kungo Airport",
      "elevation_ft": 4324.0,
      "continent": "AF",
      "iso_country": "AO",
      "iso_region": "AO-CUS",
      "municipality": "Waco Kungo",
      "gps_code": "FNWK",
      "iata_code": "CEO",
      "coordinates": "-11.4264, 15.1014"
    },
    {
      "ident": "FNXA",
      "type": "medium_airport",
      "name": "Xangongo Airport",
      "elevation_ft": 3635.0,
      "continent": "AF",
      "iso_country": "AO",
      "iso_region": "AO-CNN",
      "municipality": "Xangongo",
      "gps_code": "FNXA",
      "iata_code": "XGN",
      "coordinates": "-16.755399703979492, 14.965299606323242"
    },
    {
      "ident": "FNZE",
      "type": "small_airport",
      "name": "N'zeto Airport",
      "elevation_ft": 69.0,
      "continent": "AF",
      "iso_country": "AO",
      "iso_region": "AO-ZAI",
      "municipality": "N'zeto",
      "gps_code": "FNZE",
      "iata_code": "ARZ",
      "coordinates": "-7.259277, 12.862355"
    },
    {
      "ident": "FNZG",
      "type": "small_airport",
      "name": "Nzagi Airport",
      "elevation_ft": 2431.0,
      "continent": "AF",
      "iso_country": "AO",
      "iso_region": "AO-LNO",
      "municipality": "Nzagi",
      "gps_code": "FNZG",
      "iata_code": "NZA",
      "coordinates": "-7.716939926149999, 21.358200073200003"
    },
    {
      "ident": "JMB",
      "type": "small_airport",
      "name": "Jamba Airport",
      "elevation_ft": 4912.0,
      "continent": "AF",
      "iso_country": "AO",
      "iso_region": "AO-HUI",
      "municipality": "Jamba",
      "iata_code": "JMB",
      "coordinates": "-14.698193, 16.070148"
    }
  ]
}