{
  "country_code": "GM",
  "country_name": "Gambia",
  "total_airports": 1,
  "last_updated": "2025-04-01T00:09:45.356279",
  "types_distribution": {
    "large_airport": 1
  },
  "airports": [
    {
      "ident": "GBYD",
      "type": "large_airport",
      "name": "Banjul International Airport",
      "elevation_ft": 95.0,
      "continent": "AF",
      "iso_country": "GM",
      "iso_region": "GM-W",
      "municipality": "Yundum",
      "gps_code": "GBYD",
      "iata_code": "BJL",
      "coordinates": "13.338, -16.652201"
    }
  ]
}